{
	"id": "flavien-condition-lab",
	"name": "flavien-condition-lab",
	"title": "Flavien's Condition Lab",
	"description": "Flavien's personal fork of Condition Lab & Triggler - customized for his campaign",
	"authors": [
		{
			"name": "Flavien Gascard",
			"url": "https://github.com/Flavien-Gascard"
		}
	],
	"url": "https://github.com/Flavien-Gascard/foundry-modules-and-macro/tree/main/modules/flavien-condition-lab",
	"manifest": "https://raw.githubusercontent.com/Flavien-Gascard/foundry-modules-and-macro/main/modules/flavien-condition-lab/module.json",
	"download": "https://github.com/Flavien-Gascard/foundry-modules-and-macro/releases/download/flavien-condition-lab-v1.0.0/flavien-condition-lab.zip",
	"esmodules": ["module/flavien-condition-lab.js"],
	"styles": ["styles/flavien-condition-lab.css"],
	"languages": [
		{
			"lang": "en",
			"name": "English",
			"path": "lang/en.json"
		}
	],
	"packs": [],
	"compatibility": {
		"minimum": "12",
		"verified": "12"
	},
	"version": "1.0.0"
}
